kbgetter/__init__.py
kbgetter/KBgetter.py
kbgetter-0.1.6.dist-info/WHEEL
kbgetter-0.1.6.dist-info/METADATA
kbgetter-0.1.6.dist-info/RECORD
