Metadata-Version: 2.1
Name: kbgetter
Version: 0.1.6
Summary: Download FreshService articles to a local machine
Home-page: https://github.com/mkasfeldt/KBgetter
License: MIT
Author: Matt Kasfeldt
Author-email: matt.kasfeldt@gmail.com
Requires-Python: >=3.7,<4.0
Classifier: Development Status :: 3 - Alpha
Classifier: Intended Audience :: Developers
Classifier: Intended Audience :: Other Audience
Classifier: License :: OSI Approved :: MIT License
Classifier: Programming Language :: Python :: 3
Classifier: Programming Language :: Python :: 3.10
Classifier: Programming Language :: Python :: 3.7
Classifier: Programming Language :: Python :: 3.8
Classifier: Programming Language :: Python :: 3.9
Classifier: Topic :: Documentation
Classifier: Topic :: Text Processing :: Markup :: HTML
Classifier: Topic :: Utilities
Requires-Dist: beautifulsoup4 (>=4.10.0,<5.0.0)
Requires-Dist: requests (>=2.26.0,<3.0.0)
Requires-Dist: tinydb (>=4.5.2,<5.0.0)
Project-URL: Documentation, https://kbgetter.readthedocs.io/en/latest/
